LICENSE.md
MANIFEST.in
README.md
VERSION
setup.cfg
setup.py
pygin/VERSION.py
pygin/__init__.py
pygin/__main__.py
pygin/_management.py
pygin/collider.py
pygin/color.py
pygin/component.py
pygin/draw.py
pygin/engine.py
pygin/game_object.py
pygin/geometry.py
pygin/input.py
pygin/key_frame.py
pygin/material.py
pygin/mesh.py
pygin/scene.py
pygin/time.py
pygin.egg-info/PKG-INFO
pygin.egg-info/SOURCES.txt
pygin.egg-info/dependency_links.txt
pygin.egg-info/requires.txt
pygin.egg-info/top_level.txt
pygin/basic_objects/__init__.py
pygin/basic_objects/basic_circle.py
pygin/basic_objects/basic_particle_circ.py
pygin/basic_objects/basic_rectangle.py
pygin/basic_objects/text.py
pygin/components/__init__.py
pygin/components/animation.py
pygin/components/animator.py
pygin/components/circle_collider.py
pygin/components/circle_mesh.py
pygin/components/particle_system.py
pygin/components/physics.py
pygin/components/polygon_collider.py
pygin/components/polygon_mesh.py
pygin/components/text_mesh.py
pygin/components/transform.py
pygin/example_games/__init__.py
pygin/example_games/Balance/__init__.py
pygin/example_games/Balance/balance.py
pygin/example_games/Balance/animations/__init__.py
pygin/example_games/Balance/animations/circle_player_initial_animation.py
pygin/example_games/Balance/animations/litter_bounce.py
pygin/example_games/Balance/animations/obstacle_pulsing_animation.py
pygin/example_games/Balance/animations/particle_fade_animation.py
pygin/example_games/Balance/animations/player_bounce.py
pygin/example_games/Balance/animations/power_up_fade_out.py
pygin/example_games/Balance/animations/text_up_fade_out_animation.py
pygin/example_games/Balance/assets/__init__.py
pygin/example_games/Balance/assets/fonts/__init__.py
pygin/example_games/Balance/game_objects/__init__.py
pygin/example_games/Balance/game_objects/controllers/__init__.py
pygin/example_games/Balance/game_objects/controllers/background_particles_controller.py
pygin/example_games/Balance/game_objects/controllers/items_controller_wrapper.py
pygin/example_games/Balance/game_objects/controllers/main_menu_controller.py
