Metadata-Version: 2.1
Name: pygin
Version: 0.1.2.3
Summary: Simple Python Balance engine.
Home-page: https://github.com/CarlosMatheus/Pygin
Author: Aloysio, Carlos, Igor
Author-email: aloysiogl@gmail.com
License: MIT
Project-URL: Wiki, https://github.com/CarlosMatheus/Engine/wiki
Project-URL: Source, https://github.com/CarlosMatheus/Engine
Keywords: engine python pygame
Platform: UNKNOWN
Classifier: Development Status :: 3 - Alpha
Classifier: Intended Audience :: Developers
Classifier: Topic :: Games/Entertainment
Classifier: License :: OSI Approved :: MIT License
Classifier: Programming Language :: Python :: 3.5
Provides-Extra: test
